pracpred/__init__.py
pracpred/prob/__init__.py
pracpred/prob/combinatorics.py
pracpred/prob/exceptions.py
pracpred/prob/prob.py
pracpred/prob/probdist.py
pracpred/prob/randvar.py
pracpred/ratings/__init__.py
pracpred/ratings/elo.py
pracpred/scrape/__init__.py
pracpred/scrape/html_tables.py
pracpred/utils/__init__.py
pracpred/utils/misc.py
pracpred-0.2.1.dist-info/METADATA
pracpred-0.2.1.dist-info/RECORD
pracpred-0.2.1.dist-info/WHEEL
pracpred-0.2.1.dist-info/top_level.txt
