Metadata-Version: 2.1
Name: pracpred
Version: 0.2.1
Summary: Shared code used on practicallypredictable.com.
Home-page: https://github.com/practicallypredictable/pracpred
Author: Practically Predictable
Author-email: practicallypredictable@practicallypredictable.com
License: MIT
Keywords: probability statistics sports analytics board games
Platform: UNKNOWN
Classifier: Development Status :: 3 - Alpha
Classifier: License :: OSI Approved :: MIT License
Classifier: Programming Language :: Python :: 3.6
Classifier: Programming Language :: Python :: Implementation :: CPython
Classifier: Programming Language :: Python :: Implementation :: PyPy
Requires-Dist: numpy
